fatFuckSQL/__init__.py
fatFuckSQL/fatFuckSQL.py
fatFuckSQL-0.1.5.dist-info/METADATA
fatFuckSQL-0.1.5.dist-info/WHEEL
fatFuckSQL-0.1.5.dist-info/top_level.txt
fatFuckSQL-0.1.5.dist-info/RECORD
