Metadata-Version: 2.1
Name: fatFuckSQL
Version: 0.1.5
Summary: Light wrapper for asyncpg and aiomysql
Home-page: https://github.com/tsunyoku/fatFuckSQL
Author: tsunyoku
Author-email: tsunyoku@gmail.com
License: UNKNOWN
Platform: UNKNOWN
Classifier: Programming Language :: Python :: 3
Classifier: License :: OSI Approved :: MIT License
Classifier: Operating System :: OS Independent
Requires-Python: >=3.8
Requires-Dist: asyncpg
Requires-Dist: aiomysql
